Metadata-Version: 2.1
Name: wake
Version: 0.11.0
Summary: 🍰 Making Wikipedia and Wikidata Processing Easy, Like Eating a Piece of Cake
Home-page: https://github.com/DanielJDufour/wake
Author: Daniel J. Dufour
Author-email: daniel.j.dufour@gmail.com
License: UNKNOWN
Download-URL: https://github.com/DanielJDufour/wake/tarball/download
Keywords: python,wiki,wikidata,wikipedia
Platform: UNKNOWN
Classifier: Programming Language :: Python :: 3
Classifier: Operating System :: OS Independent
